[
  {
    "id": "3180192385090115529",
    "time": 1693328496,
    "imageUrl": "https://instagram.flim20-1.fna.fbcdn.net/v/t51.2885-15/371274413_321835046868823_3100258285743564309_n.webp?stp=dst-jpg_e35_s1080x1080&_nc_ht=instagram.flim20-1.fna.fbcdn.net&_nc_cat=107&_nc_ohc=kQIcAOPVZgIAX-3s0KQ&edm=AOQ1c0wBAAAA&ccb=7-5&oh=00_AfBJAf3Mycx0uUaYx0KogA7Ip75ZJoNa4T3cKHRsSmFJmA&oe=6505747D&_nc_sid=8b3546",
    "likes": 32,
    "comments": 0,
    "link": "https://www.instagram.com/p/CwiUB_2stfJ/",
    "text": "#london #japanhouse #japan #canvas #art #kensington #paint #acrylic #event #artshow #artist #artists #uk",
    "location": "Japan House London",
    "carousel": [
      {},
      {},
      {},
      {},
      {},
      {}
    ]
  },
  {
    "id": "3155510778286586111",
    "time": 1690386219,
    "imageUrl": "https://instagram.flim20-1.fna.fbcdn.net/v/t51.2885-15/363014754_1495777537918864_5505113779315919109_n.webp?stp=dst-jpg_e35_p1080x1080&_nc_ht=instagram.flim20-1.fna.fbcdn.net&_nc_cat=104&_nc_ohc=riT9fzKw2c4AX-xMyeT&edm=AOQ1c0wBAAAA&ccb=7-5&oh=00_AfDbiZyULY5iqzO0gGFqM-Ete8Hdt5apwpq16iwWt9h52A&oe=65041657&_nc_sid=8b3546",
    "likes": 42,
    "comments": 0,
    "link": "https://www.instagram.com/p/CvKoFWQsDj_/",
    "text": "#celtic #cross #celticcross #tomb #cemetery #london #uk #stone #tombstone #grave #vault #sunset #hanwell #quite #silence #green #nature #cemeteryphotography #cemeterylovers #wonderful",
    "location": "Hanwell, London, United Kingdom",
    "carousel": [
      {},
      {},
      {},
      {}
    ]
  }
]